Metadata-Version: 2.1
Name: AdventOfCodeInputReader
Version: 0.0.3
Summary: Package to retrieve input for Advent Of Code
Home-page: https://github.com/zeph1997/AdventOfCodeInputReader
Author: Zeph Ng
Author-email: zephngdev@gmail.com
License: MIT
Download-URL: https://github.com/zeph1997/AdventOfCodeInputReader/archive/refs/tags/v0.0.3.tar.gz
Keywords: reader,advent,of,code,api
Platform: UNKNOWN
Classifier: Development Status :: 3 - Alpha
Classifier: Intended Audience :: Developers
Classifier: Topic :: Software Development :: Build Tools
Classifier: License :: OSI Approved :: MIT License
Classifier: Programming Language :: Python :: 3
Classifier: Programming Language :: Python :: 3.4
Classifier: Programming Language :: Python :: 3.5
Classifier: Programming Language :: Python :: 3.6
Classifier: Programming Language :: Python :: 3.7
Classifier: Programming Language :: Python :: 3.8
Classifier: Programming Language :: Python :: 3.9
License-File: LICENSE
